{"mean":{"confidence_interval":{"confidence_level":0.95,"lower_bound":61904.13246916753,"upper_bound":62983.07757069285},"point_estimate":62412.7252826018,"standard_error":275.79381054438676},"median":{"confidence_interval":{"confidence_level":0.95,"lower_bound":61221.85071536145,"upper_bound":62331.78004807692},"point_estimate":61923.07721445221,"standard_error":361.9544097084781},"median_abs_dev":{"confidence_interval":{"confidence_level":0.95,"lower_bound":1344.7824343481038,"upper_bound":2188.9855735241026},"point_estimate":1845.7069565781176,"standard_error":214.4181701974466},"slope":{"confidence_interval":{"confidence_level":0.95,"lower_bound":62241.4464784122,"upper_bound":63845.59669783164},"point_estimate":63012.4818883922,"standard_error":409.92789735316006},"std_dev":{"confidence_interval":{"confidence_level":0.95,"lower_bound":1949.4705515309352,"upper_bound":3510.5529456924614},"point_estimate":2771.2747225618646,"standard_error":399.8431360227023}}